nonebot_plugin_fortnite/__init__.py
nonebot_plugin_fortnite/config.py
nonebot_plugin_fortnite/matcher.py
nonebot_plugin_fortnite/stats.py
nonebot_plugin_fornite-0.0.1.dist-info/LICENSE
nonebot_plugin_fornite-0.0.1.dist-info/METADATA
nonebot_plugin_fornite-0.0.1.dist-info/WHEEL
nonebot_plugin_fornite-0.0.1.dist-info/RECORD
