Metadata-Version: 2.3
Name: nonebot-plugin-fornite
Version: 0.0.1
Summary: 堡垒之夜插件
Home-page: https://github.com/fllesser/nonebot-plugin-fornite
Keywords: nonebot,nonebot2
Author: fllesser
Author-email: fllessive@gmail.com
Requires-Python: >=3.10,<4.0
Classifier: Programming Language :: Python :: 3
Classifier: Programming Language :: Python :: 3.10
Classifier: Programming Language :: Python :: 3.11
Classifier: Programming Language :: Python :: 3.12
Classifier: Programming Language :: Python :: 3.13
Requires-Dist: fortnite-api (>=3.2.1,<4.0.0)
Requires-Dist: nonebot-adapter-onebot (>=2.4.6,<3.0.0)
Requires-Dist: nonebot-plugin-alconna (>=0.54.2,<0.55.0)
Requires-Dist: nonebot-plugin-apscheduler (>=0.5.0,<0.6.0)
Requires-Dist: nonebot-plugin-localstore (>=0.7.3,<0.8.0)
Requires-Dist: nonebot-plugin-uninfo (>=0.6.5,<0.7.0)
Requires-Dist: nonebot2 (>=2.4.0,<3.0.0)
Project-URL: Repository, https://github.com/fllesser/nonebot-plugin-fornite
